<annotation>
	<folder>datas</folder>
	<filename>0118.jpg</filename>
	<path>C:\Users\Administrator\Desktop\datas\0118.jpg</path>
	<source>
		<database>Unknown</database>
	</source>
	<size>
		<width>1920</width>
		<height>1080</height>
		<depth>3</depth>
	</size>
	<segmented>0</segmented>
	<object>
		<name>pouring hole</name>
		<pose>Unspecified</pose>
		<truncated>0</truncated>
		<difficult>0</difficult>
		<bndbox>
			<xmin>578</xmin>
			<ymin>48</ymin>
			<xmax>671</xmax>
			<ymax>108</ymax>
		</bndbox>
	</object>
	<object>
		<name>pouring hole</name>
		<pose>Unspecified</pose>
		<truncated>1</truncated>
		<difficult>0</difficult>
		<bndbox>
			<xmin>955</xmin>
			<ymin>976</ymin>
			<xmax>1071</xmax>
			<ymax>1080</ymax>
		</bndbox>
	</object>
	<object>
		<name>pouring hole</name>
		<pose>Unspecified</pose>
		<truncated>0</truncated>
		<difficult>0</difficult>
		<bndbox>
			<xmin>1450</xmin>
			<ymin>661</ymin>
			<xmax>1566</xmax>
			<ymax>756</ymax>
		</bndbox>
	</object>
</annotation>
