<annotation>
	<folder>datas</folder>
	<filename>1084.jpg</filename>
	<path>C:\Users\Administrator\Desktop\datas\1084.jpg</path>
	<source>
		<database>Unknown</database>
	</source>
	<size>
		<width>1080</width>
		<height>1920</height>
		<depth>3</depth>
	</size>
	<segmented>0</segmented>
	<object>
		<name>pouring hole</name>
		<pose>Unspecified</pose>
		<truncated>0</truncated>
		<difficult>0</difficult>
		<bndbox>
			<xmin>226</xmin>
			<ymin>956</ymin>
			<xmax>269</xmax>
			<ymax>977</ymax>
		</bndbox>
	</object>
	<object>
		<name>pouring hole</name>
		<pose>Unspecified</pose>
		<truncated>0</truncated>
		<difficult>0</difficult>
		<bndbox>
			<xmin>568</xmin>
			<ymin>1143</ymin>
			<xmax>628</xmax>
			<ymax>1172</ymax>
		</bndbox>
	</object>
</annotation>
