<annotation>
	<folder>datas</folder>
	<filename>1345.jpg</filename>
	<path>C:\Users\Administrator\Desktop\datas\1345.jpg</path>
	<source>
		<database>Unknown</database>
	</source>
	<size>
		<width>1920</width>
		<height>1080</height>
		<depth>3</depth>
	</size>
	<segmented>0</segmented>
	<object>
		<name>pouring hole</name>
		<pose>Unspecified</pose>
		<truncated>0</truncated>
		<difficult>0</difficult>
		<bndbox>
			<xmin>573</xmin>
			<ymin>81</ymin>
			<xmax>635</xmax>
			<ymax>100</ymax>
		</bndbox>
	</object>
	<object>
		<name>pouring hole</name>
		<pose>Unspecified</pose>
		<truncated>0</truncated>
		<difficult>0</difficult>
		<bndbox>
			<xmin>913</xmin>
			<ymin>410</ymin>
			<xmax>1013</xmax>
			<ymax>515</ymax>
		</bndbox>
	</object>
</annotation>
