<annotation>
	<folder>datas</folder>
	<filename>2296.jpg</filename>
	<path>C:\Users\Administrator\Desktop\datas\2296.jpg</path>
	<source>
		<database>Unknown</database>
	</source>
	<size>
		<width>1080</width>
		<height>1920</height>
		<depth>3</depth>
	</size>
	<segmented>0</segmented>
	<object>
		<name>pouring hole</name>
		<pose>Unspecified</pose>
		<truncated>0</truncated>
		<difficult>0</difficult>
		<bndbox>
			<xmin>534</xmin>
			<ymin>1257</ymin>
			<xmax>585</xmax>
			<ymax>1306</ymax>
		</bndbox>
	</object>
	<object>
		<name>pouring hole</name>
		<pose>Unspecified</pose>
		<truncated>0</truncated>
		<difficult>0</difficult>
		<bndbox>
			<xmin>648</xmin>
			<ymin>802</ymin>
			<xmax>695</xmax>
			<ymax>848</ymax>
		</bndbox>
	</object>
</annotation>
